decima/__init__.py
decima/constants.py
decima/cli/__init__.py
decima/cli/attributions.py
decima/cli/callback.py
decima/cli/download.py
decima/cli/finetune.py
decima/cli/modisco.py
decima/cli/predict_genes.py
decima/cli/query_cell.py
decima/cli/vep.py
decima/cli/vep_attribution.py
decima/core/__init__.py
decima/core/attribution.py
decima/core/metadata.py
decima/core/result.py
decima/data/__init__.py
decima/data/dataset.py
decima/data/preprocess.py
decima/data/read_hdf5.py
decima/data/write_hdf5.py
decima/hub/__init__.py
decima/hub/download.py
decima/interpret/__init__.py
decima/interpret/attributer.py
decima/interpret/attributions.py
decima/interpret/modisco.py
decima/model/__init__.py
decima/model/decima_model.py
decima/model/lightning.py
decima/model/loss.py
decima/model/metrics.py
decima/plot/__init__.py
decima/plot/visualize.py
decima/tools/__init__.py
decima/tools/evaluate.py
decima/tools/inference.py
decima/tools/interpret.py
decima/train/__init__.py
decima/utils/__init__.py
decima/utils/dataframe.py
decima/utils/inject.py
decima/utils/io.py
decima/utils/motifs.py
decima/utils/qc.py
decima/utils/sequence.py
decima/utils/variant.py
decima/vep/__init__.py
decima/vep/attributions.py
decima/vep/vep.py
decima-0.5.2.dist-info/licenses/LICENSE.txt
decima-0.5.2.dist-info/METADATA
decima-0.5.2.dist-info/WHEEL
decima-0.5.2.dist-info/entry_points.txt
decima-0.5.2.dist-info/top_level.txt
decima-0.5.2.dist-info/RECORD
