Metadata-Version: 2.4
Name: decima
Version: 0.5.2
Summary: Add a short description here!
Home-page: https://github.com/genentech/decima
Author: Avantika Lal
Author-email: lal.avantika@gene.com
License: Genentech Non-Commercial Software License Version 1.0
Project-URL: Documentation, https://github.com/genentech/decima
Platform: any
Classifier: Development Status :: 4 - Beta
Classifier: Programming Language :: Python
Requires-Python: >=3.9
License-File: LICENSE.txt
Requires-Dist: importlib-metadata; python_version < "3.8"
Requires-Dist: click
Requires-Dist: more_itertools
Requires-Dist: wandb
Requires-Dist: numpy
Requires-Dist: torch
Requires-Dist: pyfaidx
Requires-Dist: genomepy
Requires-Dist: grelu>=1.0.10
Requires-Dist: lightning
Requires-Dist: torchmetrics
Requires-Dist: bioframe
Requires-Dist: scipy
Requires-Dist: scikit-learn
Requires-Dist: pandas
Requires-Dist: tqdm
Requires-Dist: captum
Requires-Dist: anndata
Requires-Dist: h5py
Requires-Dist: pyBigWig
Requires-Dist: pyarrow
Requires-Dist: safetensors
Requires-Dist: tangermeme>=1.0.0
Requires-Dist: faster-modisco-lite>=3.0.0
Provides-Extra: vep
Requires-Dist: cyvcf2; extra == "vep"
Provides-Extra: plot
Requires-Dist: matplotlib; extra == "plot"
Requires-Dist: seaborn; extra == "plot"
Requires-Dist: plotnine; extra == "plot"
Provides-Extra: all
Requires-Dist: cyvcf2; extra == "all"
Requires-Dist: matplotlib; extra == "all"
Requires-Dist: seaborn; extra == "all"
Requires-Dist: plotnine; extra == "all"
Provides-Extra: testing
Requires-Dist: setuptools; extra == "testing"
Requires-Dist: pytest; extra == "testing"
Requires-Dist: pytest-cov; extra == "testing"
Dynamic: license-file
